fdfd/__init__.py
fdfd-0.0.0.dist-info/METADATA
fdfd-0.0.0.dist-info/WHEEL
fdfd-0.0.0.dist-info/top_level.txt
fdfd-0.0.0.dist-info/RECORD
